ipso_phen/__init__.py
ipso_phen/__main__.py
ipso_phen/ipso_cli.py
ipso_phen/annotations/__init__.py
ipso_phen/annotations/orm_annotations.py
ipso_phen/ipapi/__init__.py
ipso_phen/ipapi/base/__init__.py
ipso_phen/ipapi/base/image_wrapper.py
ipso_phen/ipapi/base/ip_abstract.py
ipso_phen/ipapi/base/ip_common.py
ipso_phen/ipapi/base/ipt_abstract.py
ipso_phen/ipapi/base/ipt_abstract_analyzer.py
ipso_phen/ipapi/base/ipt_abstract_merger.py
ipso_phen/ipapi/base/ipt_functional.py
ipso_phen/ipapi/base/ipt_holder.py
ipso_phen/ipapi/base/ipt_loose_pipeline.py
ipso_phen/ipapi/base/ipt_strict_pipeline.py
ipso_phen/ipapi/base/pipeline_launcher.py
ipso_phen/ipapi/base/pipeline_processor.py
ipso_phen/ipapi/class_pipelines/__init__.py
ipso_phen/ipapi/class_pipelines/ip_0017s1804_eff.py
ipso_phen/ipapi/class_pipelines/ip_004c2711_dr.py
ipso_phen/ipapi/class_pipelines/ip_007C2702_DR.py
ipso_phen/ipapi/class_pipelines/ip_008C0604_DevelopAbio.py
ipso_phen/ipapi/class_pipelines/ip_0102405_ggt.py
ipso_phen/ipapi/class_pipelines/ip_012c0629_ggt.py
ipso_phen/ipapi/class_pipelines/ip_013c2307mar.py
ipso_phen/ipapi/class_pipelines/ip_013s1801_sym.py
ipso_phen/ipapi/class_pipelines/ip_014c0609_xan.py
ipso_phen/ipapi/class_pipelines/ip_019s1804_dib.py
ipso_phen/ipapi/class_pipelines/ip_01as_btitom_1810.py
ipso_phen/ipapi/class_pipelines/ip_020s1804_nem.py
ipso_phen/ipapi/class_pipelines/ip_023s1807_bti.py
ipso_phen/ipapi/class_pipelines/ip_02as_mappi1_1810.py
ipso_phen/ipapi/class_pipelines/ip_03ac_isca01_1811.py
ipso_phen/ipapi/class_pipelines/ip_06ac_phenor_1901.py
ipso_phen/ipapi/class_pipelines/ip_arabido.py
ipso_phen/ipapi/class_pipelines/ip_blue_screen_test.py
ipso_phen/ipapi/class_pipelines/ip_brachy.py
ipso_phen/ipapi/class_pipelines/ip_brachy_sym.py
ipso_phen/ipapi/class_pipelines/ip_factory.py
ipso_phen/ipapi/class_pipelines/ip_heliasen.py
ipso_phen/ipapi/class_pipelines/ip_stress.py
ipso_phen/ipapi/class_pipelines/ip_stub.py
ipso_phen/ipapi/class_pipelines/ip_tabac.py
ipso_phen-0.7.112.546.dist-info/AUTHORS
ipso_phen-0.7.112.546.dist-info/LICENSE
ipso_phen-0.7.112.546.dist-info/METADATA
ipso_phen-0.7.112.546.dist-info/WHEEL
ipso_phen-0.7.112.546.dist-info/entry_points.txt
ipso_phen-0.7.112.546.dist-info/top_level.txt
ipso_phen-0.7.112.546.dist-info/RECORD
