Metadata-Version: 2.1
Name: ipso-phen
Version: 0.7.112.546
Summary: IPSO Phen an image processing toolbox for mass phenotyping
Home-page: http://github.com/tpmp-inra/ipso_phen
Author: Felicia Antoni Maviane Macia
Author-email: ipsophen@inra.fr
License: GPL v3
Project-URL: Bug Tracker, http://github.com/tpmp-inra/ipso_phen/issues
Project-URL: Documentation, https://ipso-phen.readthedocs.io/en/latest/index.html
Project-URL: Source Code, http://github.com/tpmp-inra/ipso_phen
Keywords: image processing Python OpenCV
Platform: Any
Classifier: Development Status :: 4 - Beta
Classifier: Environment :: MacOS X
Classifier: Environment :: Win32 (MS Windows)
Classifier: Environment :: X11 Applications
Classifier: Intended Audience :: Developers
Classifier: Intended Audience :: End Users/Desktop
Classifier: Intended Audience :: Science/Research
Classifier: License :: OSI Approved :: GNU General Public License v3 (GPLv3)
Classifier: Operating System :: OS Independent
Classifier: Programming Language :: Python :: 3.6
Classifier: Programming Language :: Python :: 3.7
Classifier: Programming Language :: Python :: 3.8
Requires-Dist: matplotlib
Requires-Dist: numpy
Requires-Dist: opencv-contrib-python
Requires-Dist: pandas
Requires-Dist: paramiko
Requires-Dist: psutil
Requires-Dist: psycopg2-binary
Requires-Dist: PySide2
Requires-Dist: scikit-image
Requires-Dist: scikit-learn
Requires-Dist: seaborn
Requires-Dist: SQLAlchemy
Requires-Dist: SQLAlchemy-Utils
Requires-Dist: tqdm
Requires-Dist: Unidecode
